BashMetaHandler/BashMetaHandler.py
BashMetaHandler/__init__.py
BashMetaHandler/__main__.py
bashmetahandler-1.1.0.dist-info/LICENSE
bashmetahandler-1.1.0.dist-info/METADATA
bashmetahandler-1.1.0.dist-info/WHEEL
bashmetahandler-1.1.0.dist-info/entry_points.txt
bashmetahandler-1.1.0.dist-info/RECORD
