Metadata-Version: 2.1
Name: BashMetaHandler
Version: 1.1.0
Summary: bmh
Home-page: https://github.com/000AG000/BashMetaHandler
License: MIT
Author: Alexander Gundermann
Author-email: 416c657861@posteo.de
Requires-Python: >=3.7,<4.0
Classifier: Development Status :: 3 - Alpha
Classifier: License :: OSI Approved :: MIT License
Classifier: Programming Language :: Python :: 3
Classifier: Programming Language :: Python :: 3.7
Classifier: Programming Language :: Python :: 3.8
Classifier: Programming Language :: Python :: 3.9
Classifier: Programming Language :: Python :: 3.10
Classifier: Programming Language :: Python :: 3.11
Classifier: Programming Language :: Python :: 3.12
Requires-Dist: click (>=8.0.1)
Requires-Dist: datetime (>=5.5,<6.0)
Requires-Dist: pexpect (>=4.9.0,<5.0.0)
Project-URL: Changelog, https://github.com/000AG000/BashMetaHandler/releases
Project-URL: Documentation, https://BashMetaHandler.readthedocs.io
Project-URL: Repository, https://github.com/000AG000/BashMetaHandler
